leet/__init__.py
leet/imgcat.py
leet/logging.py
2xh_leet-1.0.1.dist-info/WHEEL
2xh_leet-1.0.1.dist-info/METADATA
2xh_leet-1.0.1.dist-info/RECORD
